README.md
setup.py
txed/__init__.py
txed/plot.py
txed/utils.py
txed.egg-info/PKG-INFO
txed.egg-info/SOURCES.txt
txed.egg-info/dependency_links.txt
txed.egg-info/not-zip-safe
txed.egg-info/requires.txt
txed.egg-info/top_level.txt